excuse_gen/__init__.py
excuse_gen/cli.py
dev_excuse_gen-0.1.1.dist-info/METADATA
dev_excuse_gen-0.1.1.dist-info/WHEEL
dev_excuse_gen-0.1.1.dist-info/entry_points.txt
dev_excuse_gen-0.1.1.dist-info/top_level.txt
dev_excuse_gen-0.1.1.dist-info/RECORD
