Metadata-Version: 2.4
Name: dev-excuse-gen
Version: 0.1.1
Summary: Generate realistic programming excuses
Author: Manish Tiwari
Requires-Python: >3.8
